__init__.py
navigate/VERSION
navigate/__init__.py
navigate/_commit.py
navigate/main.py
navigate/config/__init__.py
navigate/config/config.py
navigate/config/configuration.yaml
navigate/config/configuration_database.py
navigate/config/experiment.yml
navigate/config/gui_configuration.yml
navigate/config/multi_positions.yml
navigate/config/rest_api_config.yml
navigate/config/synthetic_configuration.yaml
navigate/config/waveform_constants.yml
navigate/config/waveform_templates.yml
navigate/controller/__init__.py
navigate/controller/configuration_controller.py
navigate/controller/configurator.py
navigate/controller/controller.py
navigate/controller/thread_pool.py
navigate/controller/sub_controllers/__init__.py
navigate/controller/sub_controllers/acquire_bar.py
navigate/controller/sub_controllers/adaptive_optics.py
navigate/controller/sub_controllers/autofocus.py
navigate/controller/sub_controllers/camera_map.py
navigate/controller/sub_controllers/camera_settings.py
navigate/controller/sub_controllers/camera_view.py
navigate/controller/sub_controllers/channels_settings.py
navigate/controller/sub_controllers/channels_tab.py
navigate/controller/sub_controllers/feature_advanced_setting.py
navigate/controller/sub_controllers/features_popup.py
navigate/controller/sub_controllers/gui.py
navigate/controller/sub_controllers/histogram.py
navigate/controller/sub_controllers/ilastik.py
navigate/controller/sub_controllers/keystrokes.py
navigate/controller/sub_controllers/menus.py
navigate/controller/sub_controllers/microscope_popup.py
navigate/controller/sub_controllers/multiposition.py
navigate/controller/sub_controllers/plugins.py
navigate/controller/sub_controllers/stages.py
navigate/controller/sub_controllers/tiling.py
navigate/controller/sub_controllers/waveform_popup.py
navigate/controller/sub_controllers/waveform_tab.py
navigate/log_files/__init__.py
navigate/log_files/filters.py
navigate/log_files/log_functions.py
navigate/log_files/logging.yml
navigate_micro-0.0.9.dist-info/licenses/LICENSE.md
navigate_micro-0.0.9.dist-info/METADATA
navigate_micro-0.0.9.dist-info/WHEEL
navigate_micro-0.0.9.dist-info/entry_points.txt
navigate_micro-0.0.9.dist-info/top_level.txt
navigate_micro-0.0.9.dist-info/RECORD
